[ {
  "event_info" : {
    "date" : "05/12/2025 10:15:53",
    "sequence" : 1700,
    "date_format" : "dd/mm/rrrr hh24:mi:ss",
    "dml_operation" : "UPDATE",
    "table_name" : "DIC_EXPRESSAO",
    "tag_name" : "CMDK",
    "tasy_user" : "jfperet",
    "guid" : "4e3e91d3-f6ec-435a-8430-38d7fa08cc5c"
  },
  "server_info" : {
    "charset" : "AMERICAN_AMERICA.AL32UTF8",
    "database_version" : "19.0",
    "instance_name" : "phcdb4"
  },
  "session_info" : {
    "machine" : "YY321275",
    "os_user" : "320159315",
    "tasy_user" : "jfperet"
  },
  "primary_key_values" : [ {
    "column_name" : "CD_EXPRESSAO",
    "data_type" : "NUMBER",
    "new_value" : 1144689,
    "old_value" : 1144689
  } ],
  "column_values" : [ {
    "column_name" : "CD_EXPRESSAO",
    "data_type" : "NUMBER",
    "new_value" : 1144689,
    "old_value" : 1144689
  }, {
    "column_name" : "DT_ATUALIZACAO",
    "data_type" : "DATE",
    "new_value" : "05/12/2025 10:08:32",
    "old_value" : "05/12/2025 09:55:53"
  }, {
    "column_name" : "DT_ATUALIZACAO_NREC",
    "data_type" : "DATE",
    "new_value" : "05/12/2025 10:08:32",
    "old_value" : "05/12/2025 09:55:53"
  } ]
}, {
  "event_info" : {
    "date" : "05/12/2025 10:15:53",
    "sequence" : 1701,
    "date_format" : "dd/mm/rrrr hh24:mi:ss",
    "dml_operation" : "UPDATE",
    "table_name" : "DIC_EXPRESSAO_CUSTOM",
    "tag_name" : "CMDK",
    "tasy_user" : "jfperet",
    "guid" : "0cbf4aec-fa1f-43b0-8652-c05da69567d6"
  },
  "server_info" : {
    "charset" : "AMERICAN_AMERICA.AL32UTF8",
    "database_version" : "19.0",
    "instance_name" : "phcdb4"
  },
  "session_info" : {
    "machine" : "YY321275",
    "os_user" : "320159315",
    "tasy_user" : "jfperet"
  },
  "primary_key_values" : [ {
    "column_name" : "NR_SEQUENCIA",
    "data_type" : "NUMBER",
    "new_value" : 25027,
    "old_value" : 25027
  } ],
  "column_values" : [ {
    "column_name" : "CD_EXPRESSAO",
    "data_type" : "NUMBER",
    "new_value" : 1144689,
    "old_value" : 1144689
  }, {
    "column_name" : "DT_ATUALIZACAO_NREC",
    "data_type" : "DATE",
    "new_value" : "05/12/2025 10:08:32",
    "old_value" : "05/12/2025 09:57:40"
  }, {
    "column_name" : "NR_SEQUENCIA",
    "data_type" : "NUMBER",
    "new_value" : 25027,
    "old_value" : 25027
  }, {
    "column_name" : "DT_ATUALIZACAO",
    "data_type" : "DATE",
    "new_value" : "05/12/2025 10:08:32",
    "old_value" : "05/12/2025 09:57:40"
  } ]
}, {
  "event_info" : {
    "date" : "05/12/2025 10:15:53",
    "sequence" : 1702,
    "date_format" : "dd/mm/rrrr hh24:mi:ss",
    "dml_operation" : "UPDATE",
    "table_name" : "DIC_EXPRESSAO_CUSTOM",
    "tag_name" : "CMDK",
    "tasy_user" : "jfperet",
    "guid" : "1a483f8e-3187-4458-b058-1ceb37b1a386"
  },
  "server_info" : {
    "charset" : "AMERICAN_AMERICA.AL32UTF8",
    "database_version" : "19.0",
    "instance_name" : "phcdb4"
  },
  "session_info" : {
    "machine" : "YY321275",
    "os_user" : "320159315",
    "tasy_user" : "jfperet"
  },
  "primary_key_values" : [ {
    "column_name" : "NR_SEQUENCIA",
    "data_type" : "NUMBER",
    "new_value" : 25028,
    "old_value" : 25028
  } ],
  "column_values" : [ {
    "column_name" : "CD_EXPRESSAO",
    "data_type" : "NUMBER",
    "new_value" : 1144689,
    "old_value" : 1144689
  }, {
    "column_name" : "DT_ATUALIZACAO_NREC",
    "data_type" : "DATE",
    "new_value" : "05/12/2025 10:08:32",
    "old_value" : "05/12/2025 09:57:53"
  }, {
    "column_name" : "NR_SEQUENCIA",
    "data_type" : "NUMBER",
    "new_value" : 25028,
    "old_value" : 25028
  }, {
    "column_name" : "DT_ATUALIZACAO",
    "data_type" : "DATE",
    "new_value" : "05/12/2025 10:08:32",
    "old_value" : "05/12/2025 09:57:53"
  } ]
}, {
  "event_info" : {
    "date" : "05/12/2025 10:15:53",
    "sequence" : 1703,
    "date_format" : "dd/mm/rrrr hh24:mi:ss",
    "dml_operation" : "UPDATE",
    "table_name" : "DIC_EXPRESSAO_CUSTOM",
    "tag_name" : "CMDK",
    "tasy_user" : "jfperet",
    "guid" : "605e44be-11e3-4e94-bec4-a6dd5cd23947"
  },
  "server_info" : {
    "charset" : "AMERICAN_AMERICA.AL32UTF8",
    "database_version" : "19.0",
    "instance_name" : "phcdb4"
  },
  "session_info" : {
    "machine" : "YY321275",
    "os_user" : "320159315",
    "tasy_user" : "jfperet"
  },
  "primary_key_values" : [ {
    "column_name" : "NR_SEQUENCIA",
    "data_type" : "NUMBER",
    "new_value" : 1144689,
    "old_value" : 1144689
  } ],
  "column_values" : [ {
    "column_name" : "DS_EXPRESSAO",
    "data_type" : "VARCHAR2",
    "new_value" : "Nova express\u00e3o WWW",
    "old_value" : "Nova express\u00e3o"
  }, {
    "column_name" : "CD_EXPRESSAO",
    "data_type" : "NUMBER",
    "new_value" : 1144689,
    "old_value" : 1144689
  }, {
    "column_name" : "DT_ATUALIZACAO_NREC",
    "data_type" : "DATE",
    "new_value" : "05/12/2025 10:08:32",
    "old_value" : "05/12/2025 09:55:54"
  }, {
    "column_name" : "NR_SEQUENCIA",
    "data_type" : "NUMBER",
    "new_value" : 1144689,
    "old_value" : 1144689
  }, {
    "column_name" : "DT_ATUALIZACAO",
    "data_type" : "DATE",
    "new_value" : "05/12/2025 10:08:32",
    "old_value" : "05/12/2025 09:55:54"
  } ]
}, {
  "event_info" : {
    "date" : "05/12/2025 10:15:53",
    "sequence" : 1750,
    "date_format" : "dd/mm/rrrr hh24:mi:ss",
    "dml_operation" : "UPDATE",
    "table_name" : "DIC_EXPRESSAO",
    "tag_name" : "CMDK",
    "tasy_user" : "jfperet",
    "guid" : "0b0ea71e-2282-471d-817f-202ffe86f5fc"
  },
  "server_info" : {
    "charset" : "AMERICAN_AMERICA.AL32UTF8",
    "database_version" : "19.0",
    "instance_name" : "phcdb4"
  },
  "session_info" : {
    "machine" : "YY321275",
    "os_user" : "320159315",
    "tasy_user" : "jfperet"
  },
  "primary_key_values" : [ {
    "column_name" : "CD_EXPRESSAO",
    "data_type" : "NUMBER",
    "new_value" : 1144689,
    "old_value" : 1144689
  } ],
  "column_values" : [ {
    "column_name" : "CD_EXPRESSAO",
    "data_type" : "NUMBER",
    "new_value" : 1144689,
    "old_value" : 1144689
  } ]
}, {
  "event_info" : {
    "date" : "05/12/2025 10:15:53",
    "sequence" : 1751,
    "date_format" : "dd/mm/rrrr hh24:mi:ss",
    "dml_operation" : "UPDATE",
    "table_name" : "DIC_EXPRESSAO_CUSTOM",
    "tag_name" : "CMDK",
    "tasy_user" : "jfperet",
    "guid" : "1ab873dd-6917-4e48-aa0c-4badc71d5c9d"
  },
  "server_info" : {
    "charset" : "AMERICAN_AMERICA.AL32UTF8",
    "database_version" : "19.0",
    "instance_name" : "phcdb4"
  },
  "session_info" : {
    "machine" : "YY321275",
    "os_user" : "320159315",
    "tasy_user" : "jfperet"
  },
  "primary_key_values" : [ {
    "column_name" : "NR_SEQUENCIA",
    "data_type" : "NUMBER",
    "new_value" : 1144689,
    "old_value" : 1144689
  } ],
  "column_values" : [ {
    "column_name" : "DS_EXPRESSAO",
    "data_type" : "VARCHAR2",
    "new_value" : "Nova express\u00e3o W",
    "old_value" : "Nova express\u00e3o WWW"
  }, {
    "column_name" : "CD_EXPRESSAO",
    "data_type" : "NUMBER",
    "new_value" : 1144689,
    "old_value" : 1144689
  }, {
    "column_name" : "DT_ATUALIZACAO_NREC",
    "data_type" : "DATE",
    "new_value" : "05/12/2025 10:15:47",
    "old_value" : "05/12/2025 10:08:32"
  }, {
    "column_name" : "NR_SEQUENCIA",
    "data_type" : "NUMBER",
    "new_value" : 1144689,
    "old_value" : 1144689
  } ]
} ]